mcp990x/__init__.py
mcp990x/mcp990x.py
mcp990x-1.1.0.dist-info/LICENSE
mcp990x-1.1.0.dist-info/METADATA
mcp990x-1.1.0.dist-info/WHEEL
mcp990x-1.1.0.dist-info/top_level.txt
mcp990x-1.1.0.dist-info/RECORD
